elloh2
