Metadata-Version: 2.1
Name: elloh
Version: 0.0.6
Summary: A small example package
Requires-Python: >=3.11
Requires-Dist: sparklog
